[
    {
        "text": "Hey there!",
        "id": 1388534400000,
        "author": "Pete Hunt"
    },
    {
        "text": "React is *great*!",
        "id": 1420070400000,
        "author": "Paul O’Shannessy"
    },
    {
        "text": "handsome",
        "id": "1450020653254",
        "author": "Hansun"
    },
    {
        "text": "papap",
        "id": 1450021913767,
        "author": "Hanxian"
    },
    {
        "id": 1450521845582,
        "author": "hanxian",
        "text": "hhhhhhh"
    },
    {
        "id": 1450521916837,
        "author": "asdfadfa",
        "text": "adfasdf"
    }
]